MANIFEST.in
README.txt
setup.py
TOPSIS_Ritik_101803600.egg-info/PKG-INFO
TOPSIS_Ritik_101803600.egg-info/SOURCES.txt
TOPSIS_Ritik_101803600.egg-info/dependency_links.txt
TOPSIS_Ritik_101803600.egg-info/requires.txt
TOPSIS_Ritik_101803600.egg-info/top_level.txt
topsis_ritik_101803600/__init__.py