Metadata-Version: 1.1
Name: TOPSIS-Ritik-101803600
Version: 0.0.1
Summary: TOPSIS package
Home-page: UNKNOWN
Author: Ritik Saxena
Author-email: rsaxena_be18@thapar.edu
License: MIT
Keywords: TOPSIS
Platform: UNKNOWN
Classifier: Development Status :: 5 - Production/Stable
Classifier: Intended Audience :: Education
Classifier: Operating System :: Microsoft :: Windows :: Windows 10
Classifier: License :: OSI Approved :: MIT License
Classifier: Programming Language :: Python :: 3
